./.gitignore
./PKG-INFO
./README.md
./py.typed
./pyproject.toml
./example/README.md
./example/__init__.py
./example/env.example
./example/pyproject.toml
./example/roboflow_example.py
./tests/test_roboflow.py
./vision_agents/plugins/roboflow/__init__.py
./vision_agents/plugins/roboflow/events.py
./vision_agents/plugins/roboflow/roboflow_cloud_processor.py
./vision_agents/plugins/roboflow/roboflow_local_processor.py
./vision_agents/plugins/roboflow/utils.py
vision_agents/plugins/roboflow/__init__.py
vision_agents/plugins/roboflow/events.py
vision_agents/plugins/roboflow/roboflow_cloud_processor.py
vision_agents/plugins/roboflow/roboflow_local_processor.py
vision_agents/plugins/roboflow/utils.py
vision_agents_plugins_roboflow-0.2.10.dist-info/METADATA
vision_agents_plugins_roboflow-0.2.10.dist-info/WHEEL
vision_agents_plugins_roboflow-0.2.10.dist-info/RECORD
