Metadata-Version: 2.4
Name: vision-agents-plugins-roboflow
Version: 0.2.10
Summary: Roboflow object detection plugin for Vision Agents
Project-URL: Documentation, https://visionagents.ai/
Project-URL: Website, https://visionagents.ai/
Project-URL: Source, https://github.com/GetStream/Vision-Agents
License-Expression: MIT
Requires-Python: >=3.10
Requires-Dist: inference-sdk>=0.17.0
Requires-Dist: numpy>=2.0.0
Requires-Dist: rfdetr>=1.3.0
Requires-Dist: vision-agents
